replopen/__init__.py
replopen-0.0.2.dist-info/LICENSE
replopen-0.0.2.dist-info/METADATA
replopen-0.0.2.dist-info/WHEEL
replopen-0.0.2.dist-info/top_level.txt
replopen-0.0.2.dist-info/RECORD
