Metadata-Version: 2.1
Name: replopen
Version: 0.0.2
Summary: Keeps open repls on repl.it
Author: SmartMozart
License: UNKNOWN
Platform: UNKNOWN
Requires-Python: >=3.6
License-File: LICENSE
